contentgrid_management_client/__init__.py
contentgrid_management_client/console.py
contentgrid_management_client/py.typed
contentgrid_management_client-0.2.2.dist-info/licenses/LICENSE
contentgrid_management_client-0.2.2.dist-info/METADATA
contentgrid_management_client-0.2.2.dist-info/WHEEL
contentgrid_management_client-0.2.2.dist-info/top_level.txt
contentgrid_management_client-0.2.2.dist-info/RECORD
