Metadata-Version: 2.4
Name: contentgrid-management-client
Version: 0.2.2
Summary: Python Client for interacting with ContentGrid Management Platform
Author-email: Ranec Belpaire <ranec.belpaire@xenit.eu>
License: Copyright 2024 Xenit Solutions
Classifier: Development Status :: 4 - Beta
Classifier: Operating System :: OS Independent
Classifier: Programming Language :: Python :: 3
Requires-Python: >=3.5
License-File: LICENSE
Requires-Dist: contentgrid-hal-client==0.2.2
Dynamic: license-file
Dynamic: requires-dist
